simplemultiproject/__init__.py
simplemultiproject/admin_command.py
simplemultiproject/admin_filter.py
simplemultiproject/admin_project.py
simplemultiproject/api.py
simplemultiproject/compat.py
simplemultiproject/environmentSetup.py
simplemultiproject/milestone.py
simplemultiproject/model.py
simplemultiproject/permission.py
simplemultiproject/roadmap.py
simplemultiproject/session.py
simplemultiproject/smp_model.py
simplemultiproject/ticket.py
simplemultiproject/timeline.py
simplemultiproject/version.py
simplemultiproject/htdocs/css/simplemultiproject.css
simplemultiproject/htdocs/js/add_version_roadmap.js
simplemultiproject/htdocs/js/admin_prefs.js
simplemultiproject/htdocs/js/disable_submit_btn.js
simplemultiproject/htdocs/js/filter_table.js
simplemultiproject/htdocs/js/jtransform.js
simplemultiproject/htdocs/js/smp_add_prefs.js
simplemultiproject/htdocs/js/smp_add_version_button.js
simplemultiproject/htdocs/js/smp_insert_column.js
simplemultiproject/htdocs/js/ticket.js
simplemultiproject/templates/admin_project.html
simplemultiproject/templates/admin_project_jinja.html
simplemultiproject/templates/admin_smp_basics.html
simplemultiproject/templates/admin_smp_basics_jinja.html
simplemultiproject/templates/roadmap_versions.html
simplemultiproject/templates/roadmap_versions_jinja.html
simplemultiproject/templates/smp_roadmap.html
simplemultiproject/templates/smp_roadmap_jinja.html
simplemultiproject/templates/version_delete.html
simplemultiproject/templates/version_delete_jinja.html
simplemultiproject/templates/version_edit.html
simplemultiproject/templates/version_edit_jinja.html
simplemultiproject/templates/version_view.html
simplemultiproject/templates/version_view_jinja.html
TracSimpleMultiProject-0.7.4.dist-info/COPYING
TracSimpleMultiProject-0.7.4.dist-info/METADATA
TracSimpleMultiProject-0.7.4.dist-info/WHEEL
TracSimpleMultiProject-0.7.4.dist-info/entry_points.txt
TracSimpleMultiProject-0.7.4.dist-info/top_level.txt
TracSimpleMultiProject-0.7.4.dist-info/RECORD
