Metadata-Version: 2.1
Name: TracSimpleMultiProject
Version: 0.7.4
Summary: Simple Multi Project plugin for managing several projects with one Trac instance.
Home-page: https://trac-hacks.org/wiki/SimpleMultiProjectPlugin
Author: Christopher Paredes, falkb, Cinc-th, Ryan J Ollos
Author-email: 
Maintainer: Cinc-th
License: BSD
Keywords: Simple Multi Project
Platform: UNKNOWN
Classifier: Framework :: Trac
Requires-Dist: Trac
